inp_kwargs/__init__.py
inp_kwargs/inp_kwargs.py
inp_kwargs-1.0.2.dist-info/LICENSE
inp_kwargs-1.0.2.dist-info/METADATA
inp_kwargs-1.0.2.dist-info/WHEEL
inp_kwargs-1.0.2.dist-info/top_level.txt
inp_kwargs-1.0.2.dist-info/RECORD
